[
    {
        "key": "sb",
        "value": "vKZfaECvS7uTocZ8JGBlB6f5",
        "domain": "facebook.com",
        "path": "/",
        "hostOnly": false,
        "creation": "2025-06-28T15:27:42.725Z",
        "lastAccessed": "2025-06-28T15:27:42.725Z"
    },
    {
        "key": "dpr",
        "value": "2.1988937854766846",
        "domain": "facebook.com",
        "path": "/",
        "hostOnly": false,
        "creation": "2025-06-28T15:27:42.725Z",
        "lastAccessed": "2025-06-28T15:27:42.725Z"
    },
    {
        "key": "c_user",
        "value": "100086649000950",
        "domain": "facebook.com",
        "path": "/",
        "hostOnly": false,
        "creation": "2025-06-28T15:27:42.725Z",
        "lastAccessed": "2025-06-28T15:27:42.725Z"
    },
    {
        "key": "wd",
        "value": "327x635",
        "domain": "facebook.com",
        "path": "/",
        "hostOnly": false,
        "creation": "2025-06-28T15:27:42.725Z",
        "lastAccessed": "2025-06-28T15:27:42.725Z"
    },
    {
        "key": "locale",
        "value": "en_US",
        "domain": "facebook.com",
        "path": "/",
        "hostOnly": false,
        "creation": "2025-06-28T15:27:42.725Z",
        "lastAccessed": "2025-06-28T15:27:42.725Z"
    },
    {
        "key": "vpd",
        "value": "v1%3B698x360x2",
        "domain": "facebook.com",
        "path": "/",
        "hostOnly": false,
        "creation": "2025-06-28T15:27:42.725Z",
        "lastAccessed": "2025-06-28T15:27:42.725Z"
    },
    {
        "key": "fbl_st",
        "value": "101437980%3BT%3A29185407",
        "domain": "facebook.com",
        "path": "/",
        "hostOnly": false,
        "creation": "2025-06-28T15:27:42.725Z",
        "lastAccessed": "2025-06-28T15:27:42.725Z"
    },
    {
        "key": "wl_cbv",
        "value": "v2%3Bclient_version%3A2856%3Btimestamp%3A1751124447",
        "domain": "facebook.com",
        "path": "/",
        "hostOnly": false,
        "creation": "2025-06-28T15:27:42.725Z",
        "lastAccessed": "2025-06-28T15:27:42.725Z"
    },
    {
        "key": "datr",
        "value": "4AlgaC_DMWdpyhNIhA04Xk1o",
        "domain": "facebook.com",
        "path": "/",
        "hostOnly": false,
        "creation": "2025-06-28T15:27:42.725Z",
        "lastAccessed": "2025-06-28T15:27:42.725Z"
    },
    {
        "key": "fr",
        "value": "1NwOIlCpLrbj58x0t.AWc11HFdukAi-x5ckSiLV18vdoVvROhc4M8NfH8Wrmg7KwJVWGc.BoYAng..AAA.0.0.BoYAng.AWdlp_NBYVk7be7x5m9A9VHvNms",
        "domain": "facebook.com",
        "path": "/",
        "hostOnly": false,
        "creation": "2025-06-28T15:27:42.725Z",
        "lastAccessed": "2025-06-28T15:27:42.725Z"
    },
    {
        "key": "xs",
        "value": "30%3AUuZZjRhJBcDaAg%3A2%3A1751099143%3A-1%3A-1%3A%3AAcUvqgQ1aDZuzacoVpqDAAV3szoa4uZeOMUbfC8P_g",
        "domain": "facebook.com",
        "path": "/",
        "hostOnly": false,
        "creation": "2025-06-28T15:27:42.725Z",
        "lastAccessed": "2025-06-28T15:27:42.725Z"
    }
]
